{
  "timestamp": "2025-04-02T01:42:23.913Z",
  "metrics": {
    "duration": 107497,
    "totalDuration": 108931
  },
  "preview": {
    "hours": "https://hours-autonomyhero-2024--preview-feature-further-refi-tp9aonfl.web.app",
    "admin": "https://admin-autonomyhero-2024--preview-feature-further-refi-guk9vhf0.web.app",
    "channelId": "preview-feature-further-refi-20250402"
  },
  "workflow": {
    "options": {
      "verbose": false,
      "skipTests": false,
      "skipBuild": false,
      "skipDeploy": false,
      "skipPr": false,
      "skipBundleCheck": false,
      "skipDeadCodeCheck": false,
      "skipDocsCheck": false,
      "skipDocsFreshnessCheck": false,
      "skipWorkflowValidation": false,
      "skipHealthCheck": false,
      "skipAdvancedChecks": false
    },
    "git": {
      "branch": "feature/further-refindment-of-workflow-"
    },
    "steps": [
      {
        "name": "Authentication",
        "phase": "Setup",
        "result": {
          "success": true
        },
        "duration": 5056,
        "timestamp": "2025-04-02T01:40:41.477Z"
      },
      {
        "name": "Dependency Check",
        "phase": "Setup",
        "result": {
          "success": true
        },
        "duration": 291,
        "timestamp": "2025-04-02T01:40:41.768Z"
      },
      {
        "name": "Setup Phase",
        "phase": "Setup",
        "result": {
          "success": true
        },
        "duration": 5348,
        "timestamp": "2025-04-02T01:40:41.769Z"
      },
      {
        "name": "Package Analysis",
        "phase": "Validation",
        "result": {
          "success": true
        },
        "duration": 2,
        "timestamp": "2025-04-02T01:40:41.772Z"
      },
      {
        "name": "Documentation Check",
        "phase": "Validation",
        "result": {
          "success": true
        },
        "duration": 1,
        "timestamp": "2025-04-02T01:40:51.889Z"
      },
      {
        "name": "Advanced Checks",
        "phase": "Validation",
        "result": {
          "success": true
        },
        "duration": 0,
        "timestamp": "2025-04-02T01:41:46.890Z"
      },
      {
        "name": "Quality Checks",
        "phase": "Validation",
        "result": {
          "success": true
        },
        "duration": 65119,
        "timestamp": "2025-04-02T01:41:46.891Z"
      },
      {
        "name": "Validation Phase",
        "phase": "Validation",
        "result": {
          "success": true
        },
        "duration": 65122,
        "timestamp": "2025-04-02T01:41:46.892Z"
      },
      {
        "name": "Package Build",
        "phase": "Build",
        "result": {
          "success": true
        },
        "duration": 12605,
        "timestamp": "2025-04-02T01:41:59.522Z"
      },
      {
        "name": "Build Phase",
        "phase": "Build",
        "result": {
          "success": true
        },
        "duration": 12629,
        "timestamp": "2025-04-02T01:41:59.523Z"
      },
      {
        "name": "Create Channel ID",
        "phase": "Deploy",
        "result": {
          "success": true
        },
        "duration": 37,
        "timestamp": "2025-04-02T01:41:59.562Z"
      },
      {
        "name": "Deploy Hours App",
        "phase": "Deploy",
        "result": {
          "success": true
        },
        "duration": 9141,
        "timestamp": "2025-04-02T01:42:08.703Z"
      },
      {
        "name": "Deploy Admin App",
        "phase": "Deploy",
        "result": {
          "success": true
        },
        "duration": 8488,
        "timestamp": "2025-04-02T01:42:17.191Z"
      },
      {
        "name": "Deploy Phase",
        "phase": "Deploy",
        "result": {
          "success": true
        },
        "duration": 17668,
        "timestamp": "2025-04-02T01:42:17.193Z"
      },
      {
        "name": "Channel Cleanup",
        "phase": "Results",
        "result": {
          "success": true
        },
        "duration": 6718,
        "timestamp": "2025-04-02T01:42:23.913Z"
      }
    ]
  },
  "warnings": [
    {
      "message": "Missing Prettier configuration file (.prettierrc)",
      "phase": "Validation",
      "step": "Quality Checks",
      "timestamp": "2025-04-02T01:40:51.888Z"
    },
    {
      "message": "Missing documentation for key features in README.md",
      "phase": "Validation",
      "step": "Documentation",
      "timestamp": "2025-04-02T01:40:51.888Z"
    },
    {
      "message": "Installation instructions incomplete in setup docs",
      "phase": "Validation",
      "step": "Documentation",
      "timestamp": "2025-04-02T01:40:51.888Z"
    },
    {
      "message": "API documentation outdated for user management endpoints",
      "phase": "Validation",
      "step": "Documentation",
      "timestamp": "2025-04-02T01:40:51.888Z"
    },
    {
      "message": "Missing JSDoc comments in auth module files",
      "phase": "Validation",
      "step": "Documentation",
      "timestamp": "2025-04-02T01:40:51.888Z"
    },
    {
      "message": "Component API documentation missing for DataTable",
      "phase": "Validation",
      "step": "Documentation",
      "timestamp": "2025-04-02T01:40:51.888Z"
    },
    {
      "message": "NPM audit found 3 high severity vulnerabilities",
      "phase": "Validation",
      "step": "Security",
      "timestamp": "2025-04-02T01:40:51.888Z"
    },
    {
      "message": "Authentication token storage needs review",
      "phase": "Validation",
      "step": "Security",
      "timestamp": "2025-04-02T01:40:51.888Z"
    },
    {
      "message": "API rate limiting not implemented",
      "phase": "Validation",
      "step": "Security",
      "timestamp": "2025-04-02T01:40:51.888Z"
    },
    {
      "message": "Unused imports in src/components/Dashboard.tsx",
      "phase": "Validation",
      "step": "Code Quality",
      "timestamp": "2025-04-02T01:40:51.889Z"
    },
    {
      "message": "Duplicate code found in utility functions",
      "phase": "Validation",
      "step": "Code Quality",
      "timestamp": "2025-04-02T01:40:51.889Z"
    },
    {
      "message": "Console.log statements found in production code",
      "phase": "Validation",
      "step": "Code Quality",
      "timestamp": "2025-04-02T01:40:51.889Z"
    },
    {
      "message": "Type 'any' used in 12 locations",
      "phase": "Validation",
      "step": "Code Quality",
      "timestamp": "2025-04-02T01:40:51.889Z"
    }
  ],
  "errors": []
}